setup.py
aguan_test.egg-info/PKG-INFO
aguan_test.egg-info/SOURCES.txt
aguan_test.egg-info/dependency_links.txt
aguan_test.egg-info/top_level.txt
testpip/__init__.py
testpip/test_install.py