Metadata-Version: 1.0
Name: aguan-test
Version: 1.0.0
Summary: a automated test tools
Home-page: https://github.com/szmgithubcode/
Author: szmgithubcode
Author-email: 13023297816@163.com
License: UNKNOWN
Platform: UNKNOWN
